leesl/__init__.py
leesl/gr.py
leesl/pp.py
leesl-0.0.2.dist-info/LICENSE
leesl-0.0.2.dist-info/METADATA
leesl-0.0.2.dist-info/WHEEL
leesl-0.0.2.dist-info/top_level.txt
leesl-0.0.2.dist-info/RECORD
