Metadata-Version: 2.1
Name: leesl
Version: 0.0.2
Summary: Python package implementing the bivariate Lee's L statistic for spatial analysis
Author: Bence Kover
Author-email: <kover.bence@gmail.com>
Keywords: spatial,transcriptomics,visium,xenium,leesl
Classifier: Development Status :: 1 - Planning
Classifier: Intended Audience :: Science/Research
Classifier: Programming Language :: Python :: 3
Classifier: Operating System :: MacOS :: MacOS X
License-File: LICENSE
Requires-Dist: numpy
Requires-Dist: pandas
Requires-Dist: scipy
Requires-Dist: scikit-learn
Requires-Dist: tqdm
Requires-Dist: joblib
Requires-Dist: statsmodels
